LICENSE
README.md
setup.py
bin/eva4-svc-bridge-udp
eva4_bridge_udp/__init__.py
eva4_bridge_udp.egg-info/PKG-INFO
eva4_bridge_udp.egg-info/SOURCES.txt
eva4_bridge_udp.egg-info/dependency_links.txt
eva4_bridge_udp.egg-info/requires.txt
eva4_bridge_udp.egg-info/top_level.txt